clamav_client/__init__.py
clamav_client/clamd.py
clamav_client/py.typed
clamav_client/scanner.py
clamav_client-0.7.0.dist-info/METADATA
clamav_client-0.7.0.dist-info/WHEEL
clamav_client-0.7.0.dist-info/licenses/LICENSE
clamav_client-0.7.0.dist-info/RECORD
