Metadata-Version: 2.4
Name: clamav-client
Version: 0.7.0
Summary: Python client library for the ClamAV antivirus.
License: GPL-2.0
License-File: LICENSE
Requires-Python: >=3.9
